interactionviz/__init__.py
interactionviz/cli/__init__.py
interactionviz/cli/viewer/__main__.py
interactionviz/gifwriter/__init__.py
interactionviz/gifwriter/gifwriter.py
interactionviz/maps/__init__.py
interactionviz/maps/map.py
interactionviz/maps/xml_loader.py
interactionviz/tracks/__init__.py
interactionviz/tracks/tracks.py
interactionviz/viewers/.DS_Store
interactionviz/viewers/__init__.py
interactionviz/viewers/arcade.py
interactionviz/viewers/static/app.js
interactionviz/viewers/static/grass.png
interactionviz/viewers/static/index.html
interactionviz/viewers/static/style.css
interactionviz/viewers/static/style.css.bk
interactionviz/viewers/viewport.py
interactionviz/viewers/web.py
interactionviz/viewers/webviewer/__init__.py
interactionviz-0.3.0.dist-info/entry_points.txt
interactionviz-0.3.0.dist-info/LICENSE
interactionviz-0.3.0.dist-info/WHEEL
interactionviz-0.3.0.dist-info/METADATA
interactionviz-0.3.0.dist-info/RECORD
