Metadata-Version: 2.1
Name: interactionviz
Version: 0.3.0
Summary: Pure Python viewer / renderer / visualizer and loader for the INTERACTION dataset
Author: Ross Hemsley
Author-email: rlhemsley@gmail.com
Requires-Python: >=3.7.5,<4.0.0
Classifier: Programming Language :: Python :: 3
Classifier: Programming Language :: Python :: 3.8
Requires-Dist: arcade (>=2.4.2,<3.0.0)
Requires-Dist: click (>=7.1.2,<8.0.0)
Requires-Dist: numpy (>=1.19.2,<2.0.0)
Requires-Dist: scipy (>=1.5.2,<2.0.0)
Requires-Dist: websockets (>=8.1,<9.0)
